control_vegas/__init__.py
control_vegas/_exceptions.py
control_vegas/_types.py
control_vegas/_wrappers.py
control_vegas/cvintegrator.py
control_vegas/functions.py
control_vegas-1.3.0.dist-info/LICENSE
control_vegas-1.3.0.dist-info/METADATA
control_vegas-1.3.0.dist-info/WHEEL
control_vegas-1.3.0.dist-info/top_level.txt
control_vegas-1.3.0.dist-info/RECORD
