Metadata-Version: 2.1
Name: control-vegas
Version: 1.3.0
Summary: A Control Variate wrapper over the vegas python package.
Author-email: Jacob Scott <jscott137@pm.me>
License: GNU GENERAL PUBLIC LICENSE
Project-URL: Github, https://github.com/crumpstrr33/control-vegas
Keywords: Monte Carlo,vegas,control variates,integration
Classifier: Development Status :: 3 - Alpha
Classifier: Programming Language :: Python :: 3.9
Classifier: Programming Language :: Python :: 3.10
Classifier: Programming Language :: Python :: 3.11
Classifier: Programming Language :: Python :: 3.12
Classifier: Intended Audience :: Science/Research
Classifier: Operating System :: OS Independent
Classifier: Topic :: Scientific/Engineering :: Mathematics
Classifier: Topic :: Scientific/Engineering :: Physics
Classifier: License :: OSI Approved :: GNU General Public License v3 (GPLv3)
Requires-Python: >=3.9
License-File: LICENSE
Requires-Dist: numpy (<1.24,>=1.22)
Requires-Dist: vegas (>=5.4)
Requires-Dist: nptyping (>=2.5)
Provides-Extra: dev
Requires-Dist: build ; extra == 'dev'
Requires-Dist: twine ; extra == 'dev'
Requires-Dist: black ; extra == 'dev'
Requires-Dist: isort ; extra == 'dev'
